tests/__init__.py
tests/test_dataset.py
tiny_imagenet_torch/__init__.py
tiny_imagenet_torch/dataset.py
tiny_imagenet_torch-0.1.0.dist-info/licenses/LICENSE
tiny_imagenet_torch-0.1.0.dist-info/METADATA
tiny_imagenet_torch-0.1.0.dist-info/WHEEL
tiny_imagenet_torch-0.1.0.dist-info/top_level.txt
tiny_imagenet_torch-0.1.0.dist-info/RECORD
