Metadata-Version: 2.4
Name: tiny-imagenet-torch
Version: 0.1.0
Summary: TinyImageNet dataset for PyTorch
Home-page: https://github.com/ligerlac/tiny-imagenet-torch
Author: Lino Gerlach
Author-email: lino.oscar.gerlach@cern.ch
Project-URL: Bug Tracker, https://github.com/ligerlac/tiny-imagenet-torch/issues
Classifier: Programming Language :: Python :: 3
Classifier: License :: OSI Approved :: MIT License
Classifier: Operating System :: OS Independent
Classifier: Topic :: Scientific/Engineering :: Artificial Intelligence
Requires-Python: >=3.6
License-File: LICENSE
Requires-Dist: torch>=1.7.0
Requires-Dist: torchvision>=0.8.0
Requires-Dist: numpy>=1.18.0
Requires-Dist: pillow>=8.0.0
Requires-Dist: tqdm>=4.50.0
Provides-Extra: dev
Requires-Dist: pytest>=6.0.0; extra == "dev"
Requires-Dist: pytest-cov>=2.10.0; extra == "dev"
Requires-Dist: flake8>=3.8.0; extra == "dev"
Requires-Dist: black>=20.8b1; extra == "dev"
Requires-Dist: isort>=5.0.0; extra == "dev"
Requires-Dist: build>=0.7.0; extra == "dev"
Requires-Dist: twine>=3.4.0; extra == "dev"
Dynamic: license-file
